pulumiverse_zitadel/__init__.py
pulumiverse_zitadel/_utilities.py
pulumiverse_zitadel/action.py
pulumiverse_zitadel/application_api.py
pulumiverse_zitadel/application_key.py
pulumiverse_zitadel/application_oidc.py
pulumiverse_zitadel/application_saml.py
pulumiverse_zitadel/default_domain_policy.py
pulumiverse_zitadel/default_label_policy.py
pulumiverse_zitadel/default_lockout_policy.py
pulumiverse_zitadel/default_login_policy.py
pulumiverse_zitadel/default_notification_policy.py
pulumiverse_zitadel/default_oidc_settings.py
pulumiverse_zitadel/default_password_complexity_policy.py
pulumiverse_zitadel/default_privacy_policy.py
pulumiverse_zitadel/domain.py
pulumiverse_zitadel/domain_policy.py
pulumiverse_zitadel/get_action.py
pulumiverse_zitadel/get_application_api.py
pulumiverse_zitadel/get_application_apis.py
pulumiverse_zitadel/get_application_oidc.py
pulumiverse_zitadel/get_application_oidcs.py
pulumiverse_zitadel/get_application_saml.py
pulumiverse_zitadel/get_application_samls.py
pulumiverse_zitadel/get_default_oidc_settings.py
pulumiverse_zitadel/get_human_user.py
pulumiverse_zitadel/get_idp_azure_ad.py
pulumiverse_zitadel/get_idp_github.py
pulumiverse_zitadel/get_idp_github_es.py
pulumiverse_zitadel/get_idp_gitlab.py
pulumiverse_zitadel/get_idp_gitlab_self_hosted.py
pulumiverse_zitadel/get_idp_google.py
pulumiverse_zitadel/get_idp_ldap.py
pulumiverse_zitadel/get_idp_oauth.py
pulumiverse_zitadel/get_idp_saml.py
pulumiverse_zitadel/get_machine_user.py
pulumiverse_zitadel/get_machine_users.py
pulumiverse_zitadel/get_org.py
pulumiverse_zitadel/get_org_idp_azure_ad.py
pulumiverse_zitadel/get_org_idp_github.py
pulumiverse_zitadel/get_org_idp_github_es.py
pulumiverse_zitadel/get_org_idp_gitlab.py
pulumiverse_zitadel/get_org_idp_gitlab_self_hosted.py
pulumiverse_zitadel/get_org_idp_google.py
pulumiverse_zitadel/get_org_idp_ldap.py
pulumiverse_zitadel/get_org_idp_oauth.py
pulumiverse_zitadel/get_org_idp_saml.py
pulumiverse_zitadel/get_org_jwt_idp.py
pulumiverse_zitadel-0.2.0.dist-info/METADATA
pulumiverse_zitadel-0.2.0.dist-info/WHEEL
pulumiverse_zitadel-0.2.0.dist-info/top_level.txt
pulumiverse_zitadel-0.2.0.dist-info/RECORD
