Metadata-Version: 2.4
Name: pulumiverse_zitadel
Version: 0.2.0
Summary: A Pulumi package for creating and managing zitadel cloud resources.
License: Apache-2.0
Project-URL: Homepage, https://www.pulumi.com
Project-URL: Repository, https://github.com/pulumiverse/pulumi-zitadel
Keywords: pulumi,zitadel,category/cloud
Requires-Python: >=3.7
Requires-Dist: parver>=0.2.1
Requires-Dist: pulumi<4.0.0,>=3.0.0
Requires-Dist: semver>=2.8.1
